framelib/__init__.py
framelib/frame.py
framelib/hub.py
framelib/models.py
framelib/neynar.py
framelib/transaction.py
framelib/warpcast.py
framelib/templates/frame.html
test/__init__.py
test/test_mint.py
test/test_render.py
test/test_transaction.py
test/test_validation.py
framelib-0.0.6.dist-info/METADATA
framelib-0.0.6.dist-info/WHEEL
framelib-0.0.6.dist-info/top_level.txt
framelib-0.0.6.dist-info/RECORD
